flask_behind_proxy.py
flask_behind_proxy-0.1.1.dist-info/LICENSE
flask_behind_proxy-0.1.1.dist-info/WHEEL
flask_behind_proxy-0.1.1.dist-info/METADATA
flask_behind_proxy-0.1.1.dist-info/RECORD
